[
  {
    "total_of_news": [
      {
        "name": "การเมือง",
        "name_en": "political",
        "total": "18"
      },
      {
        "name": "สังคมไทย",
        "name_en": "th_social",
        "total": "54"
      },
      {
        "name": "เศรษฐกิจ/การเงิน",
        "name_en": "economic",
        "total": "1"
      },
      {
        "name": "ต่างประเทศ",
        "name_en": "international",
        "total": "0"
      },
      {
        "name": "บันเทิง",
        "name_en": "entertainment",
        "total": "0"
      },
      {
        "name": "อาชญากรรม",
        "name_en": "crime",
        "total": "164"
      },
      {
        "name": "กีฬา",
        "name_en": "sport",
        "total": "0"
      },
      {
        "name": "วิทยาศาสตร์/เทคโนโลยี",
        "name_en": "science_tech",
        "total": "0"
      },
      {
        "name": "สิ่งแวดล้อม",
        "name_en": "environment",
        "total": "0"
      }
    ],
    "list": [
      {
        "date": "9/7/23",
        "political": "0",
        "sport": "0",
        "international": "0",
        "entertainment": "0",
        "science_tech": "0",
        "economic": "0",
        "th_social": "0",
        "environment": "0",
        "crime": "12",
        "total": "12"
      },
      {
        "date": "9/8/23",
        "political": "2",
        "sport": "0",
        "international": "0",
        "entertainment": "0",
        "science_tech": "0",
        "economic": "0",
        "th_social": "7",
        "environment": "0",
        "crime": "13",
        "total": "22"
      },
      {
        "date": "9/9/23",
        "political": "3",
        "sport": "0",
        "international": "0",
        "entertainment": "0",
        "science_tech": "0",
        "economic": "0",
        "th_social": "5",
        "environment": "0",
        "crime": "11",
        "total": "19"
      },
      {
        "date": "9/10/23",
        "political": "6",
        "sport": "0",
        "international": "0",
        "entertainment": "0",
        "science_tech": "0",
        "economic": "0",
        "th_social": "3",
        "environment": "0",
        "crime": "18",
        "total": "27"
      },
      {
        "date": "9/11/23",
        "political": "2",
        "sport": "0",
        "international": "0",
        "entertainment": "0",
        "science_tech": "0",
        "economic": "0",
        "th_social": "7",
        "environment": "0",
        "crime": "8",
        "total": "17"
      },
      {
        "date": "9/12/23",
        "political": "1",
        "sport": "0",
        "international": "0",
        "entertainment": "0",
        "science_tech": "0",
        "economic": "0",
        "th_social": "5",
        "environment": "0",
        "crime": "6",
        "total": "12"
      },
      {
        "date": "9/13/23",
        "political": "0",
        "sport": "0",
        "international": "0",
        "entertainment": "0",
        "science_tech": "0",
        "economic": "0",
        "th_social": "6",
        "environment": "0",
        "crime": "10",
        "total": "16"
      },
      {
        "date": "9/14/23",
        "political": "0",
        "sport": "0",
        "international": "0",
        "entertainment": "0",
        "science_tech": "0",
        "economic": "0",
        "th_social": "1",
        "environment": "0",
        "crime": "10",
        "total": "11"
      },
      {
        "date": "9/15/23",
        "political": "0",
        "sport": "0",
        "international": "0",
        "entertainment": "0",
        "science_tech": "0",
        "economic": "0",
        "th_social": "1",
        "environment": "0",
        "crime": "11",
        "total": "12"
      },
      {
        "date": "9/16/23",
        "political": "0",
        "sport": "0",
        "international": "0",
        "entertainment": "0",
        "science_tech": "0",
        "economic": "0",
        "th_social": "1",
        "environment": "0",
        "crime": "7",
        "total": "8"
      },
      {
        "date": "9/17/23",
        "political": "0",
        "sport": "0",
        "international": "0",
        "entertainment": "0",
        "science_tech": "0",
        "economic": "0",
        "th_social": "2",
        "environment": "0",
        "crime": "6",
        "total": "8"
      },
      {
        "date": "9/18/23",
        "political": "3",
        "sport": "0",
        "international": "0",
        "entertainment": "0",
        "science_tech": "0",
        "economic": "0",
        "th_social": "2",
        "environment": "0",
        "crime": "11",
        "total": "16"
      },
      {
        "date": "9/19/23",
        "political": "0",
        "sport": "0",
        "international": "0",
        "entertainment": "0",
        "science_tech": "0",
        "economic": "0",
        "th_social": "3",
        "environment": "0",
        "crime": "4",
        "total": "7"
      },
      {
        "date": "9/20/23",
        "political": "0",
        "sport": "0",
        "international": "0",
        "entertainment": "0",
        "science_tech": "0",
        "economic": "0",
        "th_social": "1",
        "environment": "0",
        "crime": "6",
        "total": "7"
      },
      {
        "date": "9/21/23",
        "political": "0",
        "sport": "0",
        "international": "0",
        "entertainment": "0",
        "science_tech": "0",
        "economic": "0",
        "th_social": "0",
        "environment": "0",
        "crime": "2",
        "total": "2"
      },
      {
        "date": "9/22/23",
        "political": "0",
        "sport": "0",
        "international": "0",
        "entertainment": "0",
        "science_tech": "0",
        "economic": "0",
        "th_social": "0",
        "environment": "0",
        "crime": "1",
        "total": "1"
      },
      {
        "date": "9/24/23",
        "political": "0",
        "sport": "0",
        "international": "0",
        "entertainment": "0",
        "science_tech": "0",
        "economic": "0",
        "th_social": "0",
        "environment": "0",
        "crime": "1",
        "total": "1"
      },
      {
        "date": "9/25/23",
        "political": "0",
        "sport": "0",
        "international": "0",
        "entertainment": "0",
        "science_tech": "0",
        "economic": "0",
        "th_social": "1",
        "environment": "0",
        "crime": "2",
        "total": "3"
      },
      {
        "date": "9/26/23",
        "political": "1",
        "sport": "0",
        "international": "0",
        "entertainment": "0",
        "science_tech": "0",
        "economic": "0",
        "th_social": "2",
        "environment": "0",
        "crime": "2",
        "total": "5"
      },
      {
        "date": "9/27/23",
        "political": "0",
        "sport": "0",
        "international": "0",
        "entertainment": "0",
        "science_tech": "0",
        "economic": "0",
        "th_social": "0",
        "environment": "0",
        "crime": "1",
        "total": "1"
      },
      {
        "date": "9/28/23",
        "political": "0",
        "sport": "0",
        "international": "0",
        "entertainment": "0",
        "science_tech": "0",
        "economic": "0",
        "th_social": "0",
        "environment": "0",
        "crime": "3",
        "total": "3"
      },
      {
        "date": "10/2/23",
        "political": "0",
        "sport": "0",
        "international": "0",
        "entertainment": "0",
        "science_tech": "0",
        "economic": "0",
        "th_social": "0",
        "environment": "0",
        "crime": "1",
        "total": "1"
      },
      {
        "date": "10/3/23",
        "political": "0",
        "sport": "0",
        "international": "0",
        "entertainment": "0",
        "science_tech": "0",
        "economic": "0",
        "th_social": "0",
        "environment": "0",
        "crime": "1",
        "total": "1"
      },
      {
        "date": "10/10/23",
        "political": "0",
        "sport": "0",
        "international": "0",
        "entertainment": "0",
        "science_tech": "0",
        "economic": "0",
        "th_social": "0",
        "environment": "0",
        "crime": "2",
        "total": "2"
      },
      {
        "date": "10/11/23",
        "political": "0",
        "sport": "0",
        "international": "0",
        "entertainment": "0",
        "science_tech": "0",
        "economic": "1",
        "th_social": "0",
        "environment": "0",
        "crime": "0",
        "total": "1"
      },
      {
        "date": "10/18/23",
        "political": "0",
        "sport": "0",
        "international": "0",
        "entertainment": "0",
        "science_tech": "0",
        "economic": "0",
        "th_social": "0",
        "environment": "0",
        "crime": "1",
        "total": "1"
      },
      {
        "date": "10/19/23",
        "political": "0",
        "sport": "0",
        "international": "0",
        "entertainment": "0",
        "science_tech": "0",
        "economic": "0",
        "th_social": "1",
        "environment": "0",
        "crime": "0",
        "total": "1"
      },
      {
        "date": "10/28/23",
        "political": "0",
        "sport": "0",
        "international": "0",
        "entertainment": "0",
        "science_tech": "0",
        "economic": "0",
        "th_social": "1",
        "environment": "0",
        "crime": "0",
        "total": "1"
      },
      {
        "date": "11/2/23",
        "political": "0",
        "sport": "0",
        "international": "0",
        "entertainment": "0",
        "science_tech": "0",
        "economic": "0",
        "th_social": "0",
        "environment": "0",
        "crime": "3",
        "total": "3"
      },
      {
        "date": "11/14/23",
        "political": "0",
        "sport": "0",
        "international": "0",
        "entertainment": "0",
        "science_tech": "0",
        "economic": "0",
        "th_social": "0",
        "environment": "0",
        "crime": "1",
        "total": "1"
      },
      {
        "date": "11/15/23",
        "political": "0",
        "sport": "0",
        "international": "0",
        "entertainment": "0",
        "science_tech": "0",
        "economic": "0",
        "th_social": "1",
        "environment": "0",
        "crime": "1",
        "total": "2"
      },
      {
        "date": "11/16/23",
        "political": "0",
        "sport": "0",
        "international": "0",
        "entertainment": "0",
        "science_tech": "0",
        "economic": "0",
        "th_social": "1",
        "environment": "0",
        "crime": "2",
        "total": "3"
      },
      {
        "date": "11/17/23",
        "political": "0",
        "sport": "0",
        "international": "0",
        "entertainment": "0",
        "science_tech": "0",
        "economic": "0",
        "th_social": "0",
        "environment": "0",
        "crime": "1",
        "total": "1"
      },
      {
        "date": "11/30/23",
        "political": "0",
        "sport": "0",
        "international": "0",
        "entertainment": "0",
        "science_tech": "0",
        "economic": "0",
        "th_social": "0",
        "environment": "0",
        "crime": "2",
        "total": "2"
      },
      {
        "date": "12/1/23",
        "political": "0",
        "sport": "0",
        "international": "0",
        "entertainment": "0",
        "science_tech": "0",
        "economic": "0",
        "th_social": "2",
        "environment": "0",
        "crime": "2",
        "total": "4"
      },
      {
        "date": "12/18/23",
        "political": "0",
        "sport": "0",
        "international": "0",
        "entertainment": "0",
        "science_tech": "0",
        "economic": "0",
        "th_social": "1",
        "environment": "0",
        "crime": "2",
        "total": "3"
      }
    ]
  }
]
